{
  "name": "Polly Logan",
  "age": 44,
  "address": {
    "street": "Pehe River",
    "city": "Woteil",
    "state": "ND",
    "zip": "79533"
  },
  "contact": {
    "phone": "(983) 778-5980",
    "servicePhone": "800558791"
  },
  "birthday": "2001-10-14T03:30:16.571Z",
  "ip": "132.3.231.55",
  "foo": "bar",
  "profile": {
    "about": "Zus kedad meg hus zugpumu og jila na puitaoju suzzeg bece iz vicgegu peju jipnif nimgofit pi pukid. Emaal buki unra nuhted ved rawablim ra re teeni juikupi mo iwitiwka. Vul taj ceri neb po jaeha ulesor silzon ku wik pukiwu veocib. Ural atos bu farbo guf pu koc la udu co hocwim wo. Co civ biri fohir matiteg rin awtaco aza zibunu ju on hamfuva.",
    "bio": "Emabazkoc galiro pe konidcak ezo fanraguci tedecur hificupi wif zac isretga uwaecicet bittief notek foosaze. Oskaus ohoco uw kumhek elozuppot lizenbob inuuc va fubceup uzaaw su irjew fakriw ze hijiw wa ewbav. Mokocu lemen zogir da ubalekiz kadkeh rugonem fifhuw lozesu masiw pe no lod bokacvib hot meczeb elda. Lickuhluw zelop uf pecufcof tatincoh ivu teopsa kagu banote dicmerul tam ve ri. Fitsi ru nokti kujsob lov jozuge uji fahlobur sifihriw bacise mibkaruc najgedkam sehuh. Wa vara ju wurokgas giad bos ugipovsa folica jefub tol seiz egven fekul nilad ocigino cutuzcoh zusge."
  },
  "apiKey": "2a480bdd0f7c4e02007853341ccfeae8deb963ec14898b9f9ce09e7ec584edd9",
  "currency": {
    "code": "JMD",
    "name": "Jamaica Dollar"
  }
}